{
    "name": "mUSO Token",
    "website": "https://mirror.finance",
    "description": "Wrapped Mirror USO Token.",
    "explorer": "https://etherscan.io/token/0x31c63146a635EB7465e5853020b39713AC356991",
    "links": [
        {
            "name": "twitter",
            "url": "https://twitter.com/mirror_protocol",
            "handle": "MirrorProtocol"
        },
        {
            "name": "discord",
            "url": "https://twitter.com/mirror_protocol",
            "handle": "MirrorProtocol"
        },
        {
            "name": "telegram",
            "url": "https://t.me/mirror_protocol",
            "handle": "MirrorProtocol"
        },
        {
            "name": "medium",
            "url": "https://medium.com/@mirror-protocol",
            "handle": "MirrorProtocol"
        }
    ],
    "type": "ERC20",
    "symbol": "mUSO",
    "decimals": 18,
    "status": "active",
    "id": "0x31c63146a635EB7465e5853020b39713AC356991"
}